Metadata-Version: 2.1
Name: typescript
Version: 0.0.12
Summary: TypeScript for Python
Home-page: https://github.com/ian-sawyer/TypeScript-for-Python
Author: Microsoft Corporation
Author-email: ian.sawyer@microsoft.com
License: UNKNOWN
Platform: UNKNOWN
Classifier: Programming Language :: Python :: 3
Classifier: License :: OSI Approved :: MIT License
Classifier: Operating System :: OS Independent
Requires-Python: >=3.6
